xzinfra_mineru_mcp/__init__.py
xzinfra_mineru_mcp/cli.py
xzinfra_mineru_mcp/config.py
xzinfra_mineru_mcp/document_parser.py
xzinfra_mineru_mcp/file_search.py
xzinfra_mineru_mcp/server.py
xzinfra_mineru_mcp-0.1.0.dist-info/METADATA
xzinfra_mineru_mcp-0.1.0.dist-info/WHEEL
xzinfra_mineru_mcp-0.1.0.dist-info/entry_points.txt
xzinfra_mineru_mcp-0.1.0.dist-info/RECORD
